netswift_cli/README.md
netswift_cli/employee_absent.db
netswift_cli/netswift_cli.py
netswift_cli/requirements.txt
netswift_cli-0.1.2.dist-info/METADATA
netswift_cli-0.1.2.dist-info/WHEEL
netswift_cli-0.1.2.dist-info/entry_points.txt
netswift_cli-0.1.2.dist-info/RECORD
