Metadata-Version: 2.1
Name: netswift-cli
Version: 0.1.2
Summary: A simple CLI application to manage NetSwift employee attendance
Author: Rehmat Alam
Author-email: rehmat@netswift.pk
Requires-Python: >=3.7,<4.0
Classifier: Programming Language :: Python :: 3
Classifier: Programming Language :: Python :: 3.7
Classifier: Programming Language :: Python :: 3.8
Classifier: Programming Language :: Python :: 3.9
Classifier: Programming Language :: Python :: 3.10
Classifier: Programming Language :: Python :: 3.11
Requires-Dist: tabulate (>=0.9.0,<0.10.0)
Requires-Dist: typer (>=0.9.0,<0.10.0)
